{"last_update":"2026-01-14T17:41:01.829Z","dolars":[{"ric":"ARS=BNAR","title":"Dólar oficial","order":1,"buy":"","sell":1480,"diff":-0.3,"last_update_text":""},{"ric":"ARST=","title":"Dólar tarjeta","order":2,"buy":"","sell":1924,"diff":-0.3,"last_update_text":""},{"ric":"ARSB=","title":"Dólar blue","order":3,"buy":"","sell":1515,"diff":0.7,"last_update_text":""},{"ric":"ARSCONT=","title":"Dólar CCL 1","order":"-","buy":"","sell":"","diff":"","last_update_text":""},{"ric":"ARSMEP=","title":"Dólar MEP","order":4,"buy":"","sell":"","diff":"","last_update_text":""},{"ric":"CR=","title":"Riesgo País *","order":6,"buy":"","sell":589,"diff":2.1,"last_update_text":""},{"ric":"ARSCONT2=","title":"Dólar CCL 2","order":"-","buy":"","sell":"","diff":"","last_update_text":""},{"ric":"ARUSDCEDEAR=","title":"CONTADO CON LIQUI","order":5,"buy":"","sell":"","diff":"","last_update_text":""},{"ric":"ARSVHM=BNAR","title":"Dólar Mayorista","order":"-","buy":"","sell":"","diff":"","last_update_text":""},{"ric":"ARSMEP0=","title":"Dólar MEP 2","order":"-","buy":"","sell":"","diff":"","last_update_text":""}],"_id":"c5c4ca47cf514d1c211b3d38a2202f71aa3e81b00bcd51871ee8020f9421a107"}