{"last_update":"2026-02-24T19:40:55.781Z","dolars":[{"ric":"ARS=BNAR","title":"Dólar oficial","order":1,"buy":"","sell":1400,"diff":0.7,"last_update_text":""},{"ric":"ARST=","title":"Dólar tarjeta","order":2,"buy":"","sell":1820,"diff":0.7,"last_update_text":""},{"ric":"ARSB=","title":"Dólar blue","order":3,"buy":"","sell":1430,"diff":0.3,"last_update_text":""},{"ric":"ARSCONT=","title":"Dólar CCL 1","order":"-","buy":"","sell":"","diff":"","last_update_text":""},{"ric":"ARSMEP=","title":"Dólar MEP","order":4,"buy":"","sell":"","diff":"","last_update_text":""},{"ric":"CR=","title":"Riesgo País *","order":6,"buy":"","sell":545,"diff":2.3,"last_update_text":""},{"ric":"ARSCONT2=","title":"Dólar CCL 2","order":"-","buy":"","sell":"","diff":"","last_update_text":""},{"ric":"ARUSDCEDEAR=","title":"CONTADO CON LIQUI","order":5,"buy":"","sell":"","diff":"","last_update_text":""},{"ric":"ARSVHM=BNAR","title":"Dólar Mayorista","order":"-","buy":"","sell":"","diff":"","last_update_text":""},{"ric":"ARSMEP0=","title":"Dólar MEP 2","order":"-","buy":"","sell":"","diff":"","last_update_text":""}],"_id":"1a7046112ea1c8ff2a8252c1e9c00d9c32fbfcdfb6a9ef77081f96d9aecf051a"}